geckodriver_autoinstaller/__init__.py
geckodriver_autoinstaller/utils.py
geckodriver_autoinstaller-0.1.0.dist-info/LICENSE
geckodriver_autoinstaller-0.1.0.dist-info/METADATA
geckodriver_autoinstaller-0.1.0.dist-info/WHEEL
geckodriver_autoinstaller-0.1.0.dist-info/entry_points.txt
geckodriver_autoinstaller-0.1.0.dist-info/top_level.txt
geckodriver_autoinstaller-0.1.0.dist-info/RECORD
